Workbook

Sheet Web Dev Pricing Calculator
A1: Client Name | B1: Client Value
A2: Project Name | B2: Project Value
A3: Date | B3: =TODAY()
A4: Quote Valid Until | B4: =B3+30
A5: Contact Email | B5: Email Value
A7: BASE PACKAGE SELECTION
A8: Package Type | B8: Select (X) | C8: Base Price | D8: Your Price
A9: Starter Site (4-6 pages) | C9: 2500 | D9: =IF(B9="X",C9,0)
A10: Growth Site (8-20 pages) | C10: 7500 | D10: =IF(B10="X",C10,0)
A11: Custom Site (complex) | C11: 18000 | D11: =IF(B11="X",C11,0)
A13: Selected Base: | D13: =SUM(D9:D11)
A15: PAGE COUNT ADJUSTMENTS
A16: Pages | B16: Select (X) | C16: Package | D16: Price | E16: Your Price
A17: 4-6 pages | C17: Starter | D17: 0 | E17: =IF(B17="X",D17,0)
A18: 8-10 pages | C18: Growth/Custom | D18: 0 | E18: =IF(B18="X",D18,0)
A19: 11-15 pages | C19: Growth | D19: 1500 | E19: =IF(B19="X",D19,0)
A20: 11-15 pages | C20: Custom | D20: 2000 | E20: =IF(B20="X",D20,0)
A21: 16-20 pages | C21: Growth | D21: 3000 | E21: =IF(B21="X",D21,0)
A22: 16-20 pages | C22: Custom | D22: 4000 | E22: =IF(B22="X",D22,0)
A23: 21-30 pages | C23: Custom | D23: 6000 | E23: =IF(B23="X",D23,0)
A24: 31+ pages | C24: Custom | D24: 10000 | E24: =IF(B24="X",D24,0)
A26: Page Count Total: | E26: =SUM(E17:E24)
A28: E-COMMERCE FEATURES
A29: Feature | B29: Select (X) | C29: Price | D29: Your Price
A30: No e-commerce | C30: 0 | D30: =IF(B30="X",C30,0)
A31: Simple store (5-20 products) | C31: 2750 | D31: =IF(B31="X",C31,0)
A32: Medium store (21-100 products) | C32: 5500 | D32: =IF(B32="X",C32,0)
A33: Large store (100+ products) | C33: 11500 | D33: =IF(B33="X",C33,0)
A34: Product variants (sizes/colors) | C34: 1000 | D34: =IF(B34="X",C34,0)
A35: Inventory management | C35: 1500 | D35: =IF(B35="X",C35,0)
A36: Subscriptions/recurring billing | C36: 2000 | D36: =IF(B36="X",C36,0)
A37: Advanced shipping calculations | C37: 1000 | D37: =IF(B37="X",C37,0)
A38: Multi-currency | C38: 1500 | D38: =IF(B38="X",C38,0)
A39: Product reviews system | C39: 800 | D39: =IF(B39="X",C39,0)
A41: E-commerce Total: | D41: =SUM(D30:D39)
A43: CONTENT PREPARATION
A44: Service | B44: Select (X) | C44: Price | D44: Your Price
A45: Content ready (organized) | C45: 0 | D45: =IF(B45="X",C45,0)
A46: Partial (needs organization) | C46: 750 | D46: =IF(B46="X",C46,0)
A47: Need help (writing/sourcing) | C47: 2250 | D47: =IF(B47="X",C47,0)
A48: Full copywriting (all pages) | C48: 4000 | D48: =IF(B48="X",C48,0)
A49: Professional photography | C49: 1250 | D49: =IF(B49="X",C49,0)
A50: Stock photo curation | C50: 400 | D50: =IF(B50="X",C50,0)
A52: Content Total: | D52: =SUM(D45:D50)
A54: CUSTOM FEATURES & INTEGRATIONS
A55: Feature | B55: Select (X) | C55: Price | D55: Your Price
A56: Contact form (basic) | C56: 0 | D56: =IF(B56="X",C56,0)
A57: Multi-step form | C57: 750 | D57: =IF(B57="X",C57,0)
A58: Booking system (simple) | C58: 2000 | D58: =IF(B58="X",C58,0)
A59: Booking system (complex) | C59: 4000 | D59: =IF(B59="X",C59,0)
A60: Member login/portal | C60: 4500 | D60: =IF(B60="X",C60,0)
A61: Blog with categories/tags | C61: 650 | D61: =IF(B61="X",C61,0)
A62: Newsletter signup | C62: 300 | D62: =IF(B62="X",C62,0)
A63: CRM integration (HubSpot/Salesforce) | C63: 1750 | D63: =IF(B63="X",C63,0)
A64: Payment gateway (Stripe/PayPal) | C64: 1150 | D64: =IF(B64="X",C64,0)
A65: Custom API integration | C65: 3500 | D65: =IF(B65="X",C65,0)
A66: Multi-language support (per language) | C66: 3000 | D66: =IF(B66="X",C66,0)
A67: Advanced search/filtering | C67: 2250 | D67: =IF(B67="X",C67,0)
... A74: Portfolio/gallery showcase | C74: 800 | D74: =IF(B74="X",C74,0)
A76: Features Total: | D76: =SUM(D56:D74)
A78: DESIGN COMPLEXITY
A79: Level | B79: Select (X) | C79: Price | D79: Your Price
A80: Template-based | C80: -500 | D80: =IF(B80="X",C80,0)
A81: Semi-custom (custom home/templated inner) | C81: 0 | D81: =IF(B81="X",C81,0)
A82: Fully custom (all pages from scratch) | C82: 3000 | D82: =IF(B82="X",C82,0)
A83: Complex animations | C83: 2250 | D83: =IF(B83="X",C83,0)
A84: Custom illustrations | C84: 2000 | D84: =IF(B84="X",C84,0)
A85: Video integration | C85: 850 | D85: =IF(B85="X",C85,0)
A86: Advanced UI/UX research | C86: 3500 | D86: =IF(B86="X",C86,0)
A88: Design Total: | D88: =SUM(D80:D86)
A90: TECHNICAL REQUIREMENTS
A91: Requirement | B91: Select (X) | C91: Price | D91: Your Price
A92: Performance optimization (advanced) | C92: 1150 | D92: =IF(B92="X",C92,0)
A93: Advanced SEO (schema/sitemap/redirects) | C93: 1500 | D93: =IF(B93="X",C93,0)
A94: Accessibility compliance (WCAG AA) | C94: 2250 | D94: =IF(B94="X",C94,0)
A95: Security hardening (advanced) | C95: 1500 | D95: =IF(B95="X",C95,0)
A96: Custom database | C96: 3750 | D96: =IF(B96="X",C96,0)
A97: Progressive Web App (PWA) | C97: 5000 | D97: =IF(B97="X",C97,0)
A99: Technical Total: | D99: =SUM(D92:D97)
A101: MIGRATION & DATA TRANSFER
A102: Task | B102: Select (X) | C102: Price | D102: Your Price
A103: No migration (new site) | C103: 0 | D103: =IF(B103="X",C103,0)
A104: Simple migration (10-20 pages) | C104: 1000 | D104: =IF(B104="X",C104,0)
A105: Medium migration (20-50 pages) | C105: 2000 | D105: =IF(B105="X",C105,0)
A106: Large migration (50-100 pages) | C106: 4000 | D106: =IF(B106="X",C106,0)
A107: Database migration | C107: 1500 | D107: =IF(B107="X",C107,0)
A108: E-commerce product migration (per 100) | C108: 750 | D108: =IF(B108="X",C108,0)
A109: URL redirect mapping | C109: 750 | D109: =IF(B109="X",C109,0)
A111: Migration Total: | D111: =SUM(D103:D109)
A113: TIMELINE & RUSH FEES
A114: Timeline | B114: Select (X) | C114: Multiplier | D114: Applied
A115: Standard (4-8 weeks) | C115: 1 | D115: =IF(B115="X",C115,0)
A116: Rush (2-4 weeks) | C116: 1.25 | D116: =IF(B116="X",C116,0)
A117: Express (<2 weeks) | C117: 1.5 | D117: =IF(B117="X",C117,0)
A118: Flexible (no deadline) | C118: 0.9 | D118: =IF(B118="X",C118,0)
A120: Timeline Multiplier: | D120: =MAX(D115:D118)
A122: SUBTOTAL BEFORE TIMELINE
A124: Base Package: | D124: =D13
A125: Page Adjustments: | D125: =E26
A126: E-commerce: | D126: =D41
...

Sheet Client Quote
A1: Client Name: | B1: ='Web Dev Pricing Calculator'!B1
A2: Project Name: | B2: ='Web Dev Pricing Calculator'!B2
A3: Quote Date: | B3: ='Web Dev Pricing Calculator'!B3
A4: Quote Valid Until: | B4: ='Web Dev Pricing Calculator'!B4
A6: PROJECT COST SUMMARY
A8: Base Package: | B8: ='Web Dev Pricing Calculator'!D12
A9: Page Adjustments: | B9: ='Web Dev Pricing Calculator'!E25
A10: E-Commerce: | B10: ='Web Dev Pricing Calculator'!D39
A11: Content: | B11: ='Web Dev Pricing Calculator'!D49
A12: Features: | B12: ='Web Dev Pricing Calculator'!D72
A13: Design: | B13: ='Web Dev Pricing Calculator'!D83
A14: Technical: | B14: ='Web Dev Pricing Calculator'!D93
A15: Migration: | B15: ='Web Dev Pricing Calculator'!D104
A17: SUBTOTAL: | B17: =SUM(B8:B15)
A18: Timeline Adjustment: | B18: ='Web Dev Pricing Calculator'!D129
A19: Discounts: | B19: ='Web Dev Pricing Calculator'!D139
A21: PROJECT TOTAL: | B21: =B17+B18+B19
